comexdown/__init__.py
comexdown/cli.py
comexdown/download.py
comexdown/fs.py
comexdown/tables.py
comexdown/urls.py
comexdown-1.5.2.dist-info/METADATA
comexdown-1.5.2.dist-info/WHEEL
comexdown-1.5.2.dist-info/entry_points.txt
comexdown-1.5.2.dist-info/licenses/LICENSE
comexdown-1.5.2.dist-info/RECORD
